radargeocoder/__init__.py
radargeocoder/src/__init__.py
radargeocoder/src/radargeocoder.py
radargeocoder-0.0.10.dist-info/LICENSE
radargeocoder-0.0.10.dist-info/METADATA
radargeocoder-0.0.10.dist-info/WHEEL
radargeocoder-0.0.10.dist-info/top_level.txt
radargeocoder-0.0.10.dist-info/RECORD
