Metadata-Version: 2.1
Name: radargeocoder
Version: 0.0.10
Summary: Python functions for geocoding addresses using the Radar API
Home-page: https://github.com/AdventistVirtual/radargeocoder
Author: Adventist Virtual
Author-email: <devsupport@adventistvirtual.com>
License: MIT
Classifier: License :: OSI Approved :: MIT License
Classifier: Programming Language :: Python :: 3.10
Classifier: Operating System :: OS Independent
Requires-Python: >=3.10
License-File: LICENSE
Requires-Dist: pandas
Requires-Dist: radar-python
